gettmpmail/LICENSE
gettmpmail/README.MD
gettmpmail/__init__.py
gettmpmail/allnamesformatfirst.pkl
gettmpmail/requirements.txt
gettmpmail/thirdparty.json
gettmpmail-0.12.dist-info/LICENSE.rst
gettmpmail-0.12.dist-info/METADATA
gettmpmail-0.12.dist-info/WHEEL
gettmpmail-0.12.dist-info/top_level.txt
gettmpmail-0.12.dist-info/RECORD
