Metadata-Version: 2.1
Name: gettmpmail
Version: 0.12
Summary: Generates temporary emails
Home-page: https://github.com/hansalemaos/gettmpmail
Author: Johannes Fischer
Author-email: <aulasparticularesdealemaosp@gmail.com>
License: MIT
Keywords: tempmail
Classifier: Development Status :: 4 - Beta
Classifier: Programming Language :: Python :: 3 :: Only
Classifier: Programming Language :: Python :: 3.9
Classifier: Topic :: Scientific/Engineering :: Visualization
Classifier: Topic :: Software Development :: Libraries :: Python Modules
Classifier: Topic :: Text Editors :: Text Processing
Classifier: Topic :: Text Processing :: General
Classifier: Topic :: Text Processing :: Indexing
Classifier: Topic :: Text Processing :: Filters
Classifier: Topic :: Utilities
License-File: LICENSE.rst
Requires-Dist: a-pandas-ex-apply-ignore-exceptions
Requires-Dist: a-pandas-ex-imap2df
Requires-Dist: a-pandas-ex-read-charsep-frames
Requires-Dist: adbescapes
Requires-Dist: charchef
Requires-Dist: deepcopyall
Requires-Dist: kthread-sleep
Requires-Dist: pandas
Requires-Dist: requests
